multids/__init__.py
multids/ai.py
multids/connectors/__init__.py
multids/connectors/athena.py
multids/connectors/local.py
multids/connectors/mssql.py
multids/connectors/opensearch.py
multids/connectors/s3.py
multids/connectors/sql.py
multids/connectors/sync/__init__.py
multids/connectors/sync/athena.py
multids/connectors/sync/local.py
multids/connectors/sync/mssql.py
multids/connectors/sync/s3.py
multids/connectors/sync/sql.py
multids/interfaces.py
multids-0.1.1.dist-info/METADATA
multids-0.1.1.dist-info/WHEEL
multids-0.1.1.dist-info/licenses/LICENSE
multids-0.1.1.dist-info/RECORD
