Metadata-Version: 2.4
Name: multids
Version: 0.1.1
Summary: Async multi-data-source connectors (S3, OpenSearch, Athena, MySQL, SQL Server, local files) with AI hooks.
License-File: LICENSE
Author: Khaldoun Aljasem
Author-email: khaldoun.aljasem@gmail.com
Requires-Python: >=3.11,<4.0
Classifier: Development Status :: 4 - Beta
Classifier: Intended Audience :: Developers
Classifier: License :: OSI Approved :: MIT License
Classifier: Programming Language :: Python :: 3
Classifier: Programming Language :: Python :: 3.11
Classifier: Programming Language :: Python :: 3.12
Classifier: Programming Language :: Python :: 3.13
Classifier: Programming Language :: Python :: 3.14
Provides-Extra: ai
Provides-Extra: opensearch
Provides-Extra: s3
Provides-Extra: sqlserver
Provides-Extra: sync
Requires-Dist: aioboto3 (>=10.4.0,<11.0.0) ; extra == "s3"
Requires-Dist: aiofiles (>=23.1,<24.0)
Requires-Dist: aioodbc ; (python_version < "3.12") and (extra == "sqlserver")
Requires-Dist: asyncmy (>=0.2,<0.3)
Requires-Dist: boto3 (>=1.24.59,<1.24.60) ; extra == "s3" or extra == "sync"
Requires-Dist: httpx[http2] (>=0.24.0,<0.25.0) ; extra == "opensearch"
Requires-Dist: openai (>=1.0,<2.0) ; extra == "ai"
Requires-Dist: pymysql (>=1.1,<2.0) ; extra == "sync"
Requires-Dist: pyodbc (>=4.0,<5.0) ; (python_version < "3.12") and (extra == "sqlserver" or extra == "sync")
Requires-Dist: requests (>=2.31,<3.0) ; extra == "opensearch" or extra == "sync"
Requires-Dist: sqlalchemy (>=2.0,<3.0)
Project-URL: Documentation, https://aljasem-tech.github.io/multids/
Project-URL: Homepage, https://github.com/aljasem-tech/multids
Project-URL: Repository, https://github.com/aljasem-tech/multids
